pandorapsf/__init__.py
pandorapsf/data/dichroic-transmission.csv
pandorapsf/data/nirda-wav-solution.fits
pandorapsf/data/pandora.mplstyle
pandorapsf/data/pandora_nir_psf_lowres.fits
pandorapsf/data/pandora_vis_psf_lowres.fits
pandorapsf/data/pandora_visible_qe.csv
pandorapsf/data/pixel_vs_wavelength.csv
pandorapsf/data/visda-wav-solution.fits
pandorapsf/docstrings.py
pandorapsf/plotting.py
pandorapsf/psf.py
pandorapsf/scene.py
pandorapsf/utils.py
pandorapsf-0.7.0.dist-info/LICENSE
pandorapsf-0.7.0.dist-info/METADATA
pandorapsf-0.7.0.dist-info/WHEEL
pandorapsf-0.7.0.dist-info/RECORD
