Metadata-Version: 2.3
Name: pandorapsf
Version: 0.7.0
Summary: 
Author: Christina Hedges
Author-email: christina.l.hedges@nasa.gov
Requires-Python: >=3.9,<3.13
Classifier: Programming Language :: Python :: 3
Classifier: Programming Language :: Python :: 3.9
Classifier: Programming Language :: Python :: 3.10
Classifier: Programming Language :: Python :: 3.11
Classifier: Programming Language :: Python :: 3.12
Requires-Dist: appdirs (>=1.4.4,<2.0.0)
Requires-Dist: numpy (>=1.26.0)
Requires-Dist: pandorasat (>=0.12.1)
Requires-Dist: sparse3d (>=1.0.3)
